{
  "unity": "/path/to/Unity/Hub/Editor/6000.x.x/Editor/Unity",
  "apk_dash": "/path/to/APK Dash",
  "ios_remote": {
    "mac_ip": "192.168.1.130",
    "mac_user": "pavel",
    "mac_auth": "key",
    "mac_key_path": "~/.ssh/id_ed25519",
    "mac_password": "",
    "mac_work_dir": "/Users/pavel/Desktop/MyProject",
    "progress_port": 8080,
    "widget_bundle_id": "com.example.myapp.widget",
    "widget_team_id": "XXXXXXXXXX",
    "widget_target_name": "URLImageWidget",
    "widget_folder_name": "kartoteka.widget",
    "widget_app_group_id": "group.com.example.myapp",
    "devices": [
      {"name": "iPhone 12 mini", "display_name": "iPhone 12 mini"},
      {"name": "iPad Pro",       "display_name": "iPad Pro"}
    ],
    "smb_user": "",
    "smb_password": "",
    "smb_build_path": ""
  },
  "projects": [
    {
      "name": "MyProject",
      "path": "/path/to/MyProject",
      "desc": "Android VR app",
      "build_dir": "/path/to/MyProject/Builds",
      "targets": ["android"]
    },
    {
      "name": "MyMobileProject",
      "path": "/path/to/MyMobileProject",
      "desc": "iOS and Android",
      "build_dir": "/path/to/MyMobileProject/Builds",
      "targets": ["android", "ios"]
    }
  ]
}
